bpnet_pytorch/__init__.py
bpnet_pytorch/bpnet_pytorch.py
bpnet_pytorch/data.py
bpnet_pytorch/train.py
bpnet_pytorch-0.0.2.dist-info/METADATA
bpnet_pytorch-0.0.2.dist-info/WHEEL
bpnet_pytorch-0.0.2.dist-info/top_level.txt
bpnet_pytorch-0.0.2.dist-info/RECORD
