Metadata-Version: 2.1
Name: bpnet-pytorch
Version: 0.0.2
Summary: BPNet - Pytorch
Home-page: https://github.com/dohlee/bpnet-pytorch
Author: Dohoon Lee
Author-email: dohlee.bioinfo@gmail.com
License: MIT
Keywords: artificial intelligence,genomics,functional genomics,DNA sequence
Classifier: Development Status :: 4 - Beta
Classifier: Intended Audience :: Developers
Classifier: Topic :: Scientific/Engineering :: Artificial Intelligence
Classifier: License :: OSI Approved :: MIT License
Classifier: Programming Language :: Python :: 3.9
Requires-Dist: einops (>=0.3)
Requires-Dist: numpy
Requires-Dist: torch (>=1.6)
